asranger/__init__.py
asranger/ranger.py
asranger/ranger913A.py
asranger/rangerqh.py
asranger-0.0.5.dist-info/LICENSE
asranger-0.0.5.dist-info/METADATA
asranger-0.0.5.dist-info/WHEEL
asranger-0.0.5.dist-info/top_level.txt
asranger-0.0.5.dist-info/RECORD
